[
    {
        "v": 27382,
        "c": 158.41,
        "o": 158.51,
        "h": 158.79,
        "l": 158.32,
        "t": 1603893900000
    },
    {
        "v": 48277,
        "c": 158.41,
        "o": 158.47,
        "h": 158.61,
        "l": 158.22,
        "t": 1603894200000
    },
    {
        "v": 35169,
        "c": 157.77,
        "o": 158.35,
        "h": 158.4,
        "l": 157.77,
        "t": 1603894500000
    },
    {
        "v": 38913,
        "c": 157.18,
        "o": 157.775,
        "h": 157.83,
        "l": 157.18,
        "t": 1603894800000
    },
    {
        "v": 55157,
        "c": 157.2375,
        "o": 157.18,
        "h": 157.4,
        "l": 156.8,
        "t": 1603895100000
    },
    {
        "v": 22810,
        "c": 158,
        "o": 157.12,
        "h": 158.3,
        "l": 157.12,
        "t": 1603895400000
    }
]